{
"type": "FeatureCollection",
"name": "divisas_308067",
"crs": { "type": "name", "properties": { "name": "urn:ogc:def:crs:OGC:1.3:CRS84" } },
"features": [
{ "type": "Feature", "properties": { "NOME_FAZ": "ESTANCIA SANTO ANTONIO", "ZONA": 1, "TALHAO": 1, "AREA_TOTAL": 32.391443534463413, "FAZENDA": "308067" }, "geometry": { "type": "MultiPolygon", "coordinates": [ [ [ [ -50.37432, -21.37317 ], [ -50.37601, -21.37637 ], [ -50.37895, -21.37658 ], [ -50.37913, -21.37653 ], [ -50.37917, -21.37642 ], [ -50.37976, -21.37366 ], [ -50.37957, -21.37356 ], [ -50.37432, -21.37317 ] ] ], [ [ [ -50.37056, -21.3729 ], [ -50.36997, -21.37583 ], [ -50.37005, -21.37592 ], [ -50.37595, -21.37637 ], [ -50.37427, -21.37316 ], [ -50.37056, -21.3729 ] ] ] ] } }
]
}
