{
"type": "FeatureCollection",
"name": "divisas_306829",
"crs": { "type": "name", "properties": { "name": "urn:ogc:def:crs:OGC:1.3:CRS84" } },
"features": [
{ "type": "Feature", "properties": { "NOME_FAZ": "FAZENDA SAO JOAO", "ZONA": 999, "TALHAO": 2, "AREA_TOTAL": 33.106903725521128, "FAZENDA": "306829" }, "geometry": { "type": "Polygon", "coordinates": [ [ [ -50.20446, -21.41634 ], [ -50.20748, -21.41963 ], [ -50.20919, -21.42138 ], [ -50.21206, -21.42319 ], [ -50.21258, -21.42329 ], [ -50.21262, -21.42354 ], [ -50.21308, -21.42378 ], [ -50.21322, -21.42374 ], [ -50.21108, -21.42092 ], [ -50.21009, -21.41893 ], [ -50.20933, -21.41616 ], [ -50.20921, -21.41495 ], [ -50.20922, -21.414 ], [ -50.20915, -21.41387 ], [ -50.20883, -21.41379 ], [ -50.20877, -21.41369 ], [ -50.20883, -21.41289 ], [ -50.20446, -21.41634 ] ] ] } },
{ "type": "Feature", "properties": { "NOME_FAZ": "FAZENDA SAO JOAO", "ZONA": 999, "TALHAO": 1, "AREA_TOTAL": 33.045739050734504, "FAZENDA": "306829" }, "geometry": { "type": "Polygon", "coordinates": [ [ [ -50.20229, -21.41374 ], [ -50.20252, -21.41427 ], [ -50.20443, -21.41631 ], [ -50.20869, -21.41289 ], [ -50.20883, -21.41285 ], [ -50.20895, -21.4123 ], [ -50.2089, -21.41179 ], [ -50.20893, -21.41167 ], [ -50.20914, -21.41152 ], [ -50.20919, -21.41116 ], [ -50.20918, -21.4107 ], [ -50.209, -21.41006 ], [ -50.20926, -21.4098 ], [ -50.20892, -21.40906 ], [ -50.20862, -21.40887 ], [ -50.20206, -21.4124 ], [ -50.20229, -21.41374 ] ] ] } },
{ "type": "Feature", "properties": { "NOME_FAZ": "FAZENDA SAO JOAO", "ZONA": 999, "TALHAO": 4, "AREA_TOTAL": 10.07987192133189, "FAZENDA": "306829" }, "geometry": { "type": "Polygon", "coordinates": [ [ [ -50.21672, -21.41052 ], [ -50.21613, -21.41257 ], [ -50.21701, -21.41302 ], [ -50.2181, -21.41377 ], [ -50.21873, -21.41447 ], [ -50.21903, -21.41515 ], [ -50.21982, -21.41238 ], [ -50.21972, -21.41205 ], [ -50.21914, -21.41156 ], [ -50.21799, -21.4108 ], [ -50.21672, -21.41052 ] ] ] } },
{ "type": "Feature", "properties": { "NOME_FAZ": "FAZENDA SAO JOAO", "ZONA": 999, "TALHAO": 3, "AREA_TOTAL": 10.021409940202814, "FAZENDA": "306829" }, "geometry": { "type": "Polygon", "coordinates": [ [ [ -50.21243, -21.41074 ], [ -50.21217, -21.41242 ], [ -50.21268, -21.41219 ], [ -50.21353, -21.41212 ], [ -50.21533, -21.41229 ], [ -50.21609, -21.41255 ], [ -50.21669, -21.41051 ], [ -50.2139, -21.40981 ], [ -50.21351, -21.40981 ], [ -50.21304, -21.41006 ], [ -50.21243, -21.41074 ] ] ] } },
{ "type": "Feature", "properties": { "NOME_FAZ": "FAZENDA SAO JOAO", "ZONA": 999, "TALHAO": 6, "AREA_TOTAL": 20.782629311971466, "FAZENDA": "306829" }, "geometry": { "type": "Polygon", "coordinates": [ [ [ -50.21612, -21.41261 ], [ -50.21477, -21.41735 ], [ -50.21766, -21.41983 ], [ -50.21901, -21.41521 ], [ -50.2187, -21.41448 ], [ -50.21808, -21.4138 ], [ -50.21699, -21.41305 ], [ -50.21612, -21.41261 ] ] ] } },
{ "type": "Feature", "properties": { "NOME_FAZ": "FAZENDA SAO JOAO", "ZONA": 999, "TALHAO": 5, "AREA_TOTAL": 16.314004332709548, "FAZENDA": "306829" }, "geometry": { "type": "Polygon", "coordinates": [ [ [ -50.21216, -21.41246 ], [ -50.21184, -21.41484 ], [ -50.21473, -21.41733 ], [ -50.21608, -21.41259 ], [ -50.21532, -21.41233 ], [ -50.21352, -21.41215 ], [ -50.21293, -21.41218 ], [ -50.21216, -21.41246 ] ] ] } },
{ "type": "Feature", "properties": { "NOME_FAZ": "FAZENDA SAO JOAO", "ZONA": 999, "TALHAO": 8, "AREA_TOTAL": 8.1553008237622677, "FAZENDA": "306829" }, "geometry": { "type": "Polygon", "coordinates": [ [ [ -50.21437, -21.41883 ], [ -50.21693, -21.42242 ], [ -50.21764, -21.41987 ], [ -50.21476, -21.41739 ], [ -50.21437, -21.41883 ] ] ] } },
{ "type": "Feature", "properties": { "NOME_FAZ": "FAZENDA SAO JOAO", "ZONA": 999, "TALHAO": 7, "AREA_TOTAL": 3.6666103117971449, "FAZENDA": "306829" }, "geometry": { "type": "Polygon", "coordinates": [ [ [ -50.21182, -21.41533 ], [ -50.21434, -21.41879 ], [ -50.21472, -21.41737 ], [ -50.21183, -21.41488 ], [ -50.21182, -21.41533 ] ] ] } },
{ "type": "Feature", "properties": { "NOME_FAZ": "FAZENDA SAO JOAO", "ZONA": 999, "TALHAO": 57, "AREA_TOTAL": 27.096381806390035, "FAZENDA": "306829" }, "geometry": { "type": "Polygon", "coordinates": [ [ [ -50.20284, -21.46637 ], [ -50.20349, -21.4589 ], [ -50.20314, -21.45871 ], [ -50.19983, -21.4585 ], [ -50.19937, -21.46296 ], [ -50.20234, -21.4664 ], [ -50.20263, -21.46655 ], [ -50.20284, -21.46637 ] ] ] } },
{ "type": "Feature", "properties": { "NOME_FAZ": "FAZENDA SAO JOAO", "ZONA": 999, "TALHAO": 56, "AREA_TOTAL": 16.490585014734911, "FAZENDA": "306829" }, "geometry": { "type": "Polygon", "coordinates": [ [ [ -50.20359, -21.4577 ], [ -50.20381, -21.45477 ], [ -50.2002, -21.45425 ], [ -50.19983, -21.45847 ], [ -50.20267, -21.45865 ], [ -50.20262, -21.4584 ], [ -50.20274, -21.45805 ], [ -50.20292, -21.45797 ], [ -50.20343, -21.45795 ], [ -50.20359, -21.4577 ] ] ] } },
{ "type": "Feature", "properties": { "NOME_FAZ": "FAZENDA SAO JOAO", "ZONA": 999, "TALHAO": 59, "AREA_TOTAL": 20.020789999358687, "FAZENDA": "306829" }, "geometry": { "type": "Polygon", "coordinates": [ [ [ -50.204, -21.45222 ], [ -50.20395, -21.45166 ], [ -50.20354, -21.4513 ], [ -50.20302, -21.45058 ], [ -50.20289, -21.45034 ], [ -50.20281, -21.44986 ], [ -50.20202, -21.44897 ], [ -50.20146, -21.44861 ], [ -50.20058, -21.44867 ], [ -50.20021, -21.45422 ], [ -50.20381, -21.45474 ], [ -50.204, -21.45222 ] ] ] } },
{ "type": "Feature", "properties": { "NOME_FAZ": "FAZENDA SAO JOAO", "ZONA": 999, "TALHAO": 58, "AREA_TOTAL": 12.972437013570662, "FAZENDA": "306829" }, "geometry": { "type": "MultiPolygon", "coordinates": [ [ [ [ -50.20304, -21.46495 ], [ -50.20384, -21.46503 ], [ -50.20414, -21.46172 ], [ -50.20331, -21.46162 ], [ -50.20304, -21.46495 ] ] ], [ [ [ -50.20366, -21.45745 ], [ -50.20332, -21.46158 ], [ -50.20414, -21.46168 ], [ -50.2045, -21.45778 ], [ -50.20366, -21.45745 ] ] ], [ [ [ -50.20491, -21.45183 ], [ -50.20428, -21.45163 ], [ -50.2041, -21.45172 ], [ -50.20379, -21.45535 ], [ -50.20366, -21.45742 ], [ -50.20451, -21.45774 ], [ -50.20495, -21.45201 ], [ -50.20491, -21.45183 ] ] ] ] } },
{ "type": "Feature", "properties": { "NOME_FAZ": "FAZENDA SAO JOAO", "ZONA": 999, "TALHAO": 64, "AREA_TOTAL": 11.257047829155276, "FAZENDA": "306829" }, "geometry": { "type": "Polygon", "coordinates": [ [ [ -50.20616, -21.46545 ], [ -50.20605, -21.46534 ], [ -50.20301, -21.46497 ], [ -50.20286, -21.46636 ], [ -50.20284, -21.4674 ], [ -50.20359, -21.46871 ], [ -50.20396, -21.46915 ], [ -50.20406, -21.46914 ], [ -50.20451, -21.46875 ], [ -50.20437, -21.46843 ], [ -50.20473, -21.46815 ], [ -50.20482, -21.46814 ], [ -50.20524, -21.46867 ], [ -50.20533, -21.46865 ], [ -50.20616, -21.46545 ] ] ] } },
{ "type": "Feature", "properties": { "NOME_FAZ": "FAZENDA SAO JOAO", "ZONA": 999, "TALHAO": 63, "AREA_TOTAL": 28.460357535303391, "FAZENDA": "306829" }, "geometry": { "type": "Polygon", "coordinates": [ [ [ -50.19855, -21.44225 ], [ -50.19817, -21.44607 ], [ -50.19804, -21.4464 ], [ -50.20047, -21.44643 ], [ -50.20062, -21.4463 ], [ -50.20125, -21.44533 ], [ -50.20147, -21.44516 ], [ -50.20184, -21.44534 ], [ -50.20238, -21.44597 ], [ -50.20343, -21.44598 ], [ -50.20354, -21.44582 ], [ -50.20408, -21.44062 ], [ -50.20381, -21.44061 ], [ -50.19855, -21.44225 ] ] ] } },
{ "type": "Feature", "properties": { "NOME_FAZ": "FAZENDA SAO JOAO", "ZONA": 999, "TALHAO": 60, "AREA_TOTAL": 16.62361882569995, "FAZENDA": "306829" }, "geometry": { "type": "Polygon", "coordinates": [ [ [ -50.1978, -21.44897 ], [ -50.19735, -21.45382 ], [ -50.20017, -21.45421 ], [ -50.20054, -21.44867 ], [ -50.1978, -21.44897 ] ] ] } },
{ "type": "Feature", "properties": { "NOME_FAZ": "FAZENDA SAO JOAO", "ZONA": 999, "TALHAO": 62, "AREA_TOTAL": 19.749490093353693, "FAZENDA": "306829" }, "geometry": { "type": "Polygon", "coordinates": [ [ [ -50.19402, -21.44381 ], [ -50.19381, -21.44444 ], [ -50.19392, -21.4451 ], [ -50.19432, -21.44581 ], [ -50.19543, -21.44737 ], [ -50.19577, -21.44741 ], [ -50.19799, -21.44641 ], [ -50.19813, -21.44606 ], [ -50.19851, -21.44226 ], [ -50.19556, -21.44278 ], [ -50.19429, -21.44341 ], [ -50.19402, -21.44381 ] ] ] } },
{ "type": "Feature", "properties": { "NOME_FAZ": "FAZENDA SAO JOAO", "ZONA": 999, "TALHAO": 61, "AREA_TOTAL": 6.6337506170680083, "FAZENDA": "306829" }, "geometry": { "type": "Polygon", "coordinates": [ [ [ -50.19602, -21.44987 ], [ -50.19643, -21.45224 ], [ -50.19617, -21.45371 ], [ -50.19731, -21.45382 ], [ -50.19776, -21.44898 ], [ -50.19638, -21.44932 ], [ -50.19617, -21.44943 ], [ -50.19602, -21.44987 ] ] ] } },
{ "type": "Feature", "properties": { "NOME_FAZ": "FAZENDA SAO JOAO", "ZONA": 999, "TALHAO": 46, "AREA_TOTAL": 17.183969343286897, "FAZENDA": "306829" }, "geometry": { "type": "Polygon", "coordinates": [ [ [ -50.19246, -21.4645 ], [ -50.19288, -21.4605 ], [ -50.18954, -21.45781 ], [ -50.18918, -21.46205 ], [ -50.19246, -21.4645 ] ] ] } },
{ "type": "Feature", "properties": { "NOME_FAZ": "FAZENDA SAO JOAO", "ZONA": 999, "TALHAO": 45, "AREA_TOTAL": 17.327427564149538, "FAZENDA": "306829" }, "geometry": { "type": "Polygon", "coordinates": [ [ [ -50.19258, -21.46458 ], [ -50.19611, -21.46719 ], [ -50.19618, -21.46719 ], [ -50.19646, -21.46346 ], [ -50.19303, -21.46061 ], [ -50.19289, -21.46076 ], [ -50.19258, -21.46458 ] ] ] } },
{ "type": "Feature", "properties": { "NOME_FAZ": "FAZENDA SAO JOAO", "ZONA": 999, "TALHAO": 48, "AREA_TOTAL": 24.496502457644116, "FAZENDA": "306829" }, "geometry": { "type": "Polygon", "coordinates": [ [ [ -50.18952, -21.45778 ], [ -50.19274, -21.46032 ], [ -50.19651, -21.46342 ], [ -50.1965, -21.46231 ], [ -50.19639, -21.46159 ], [ -50.19616, -21.46076 ], [ -50.19586, -21.46026 ], [ -50.19414, -21.45846 ], [ -50.18983, -21.45428 ], [ -50.18952, -21.45778 ] ] ] } },
{ "type": "Feature", "properties": { "NOME_FAZ": "FAZENDA SAO JOAO", "ZONA": 999, "TALHAO": 47, "AREA_TOTAL": 6.0042592600215237, "FAZENDA": "306829" }, "geometry": { "type": "Polygon", "coordinates": [ [ [ -50.19653, -21.46231 ], [ -50.19655, -21.46345 ], [ -50.20147, -21.46727 ], [ -50.20067, -21.46647 ], [ -50.19623, -21.46084 ], [ -50.19653, -21.46231 ] ] ] } },
{ "type": "Feature", "properties": { "NOME_FAZ": "FAZENDA SAO JOAO", "ZONA": 999, "TALHAO": 53, "AREA_TOTAL": 33.194285254002992, "FAZENDA": "306829" }, "geometry": { "type": "Polygon", "coordinates": [ [ [ -50.18529, -21.44653 ], [ -50.19016, -21.45011 ], [ -50.19045, -21.44605 ], [ -50.19077, -21.44303 ], [ -50.19011, -21.4419 ], [ -50.18969, -21.44085 ], [ -50.18957, -21.4401 ], [ -50.18947, -21.43994 ], [ -50.18928, -21.43992 ], [ -50.18917, -21.44003 ], [ -50.18871, -21.44096 ], [ -50.18529, -21.44653 ] ] ] } },
{ "type": "Feature", "properties": { "NOME_FAZ": "FAZENDA SAO JOAO", "ZONA": 999, "TALHAO": 55, "AREA_TOTAL": 20.304434267483092, "FAZENDA": "306829" }, "geometry": { "type": "MultiPolygon", "coordinates": [ [ [ [ -50.19594, -21.45563 ], [ -50.19617, -21.45757 ], [ -50.19704, -21.45983 ], [ -50.1973, -21.45385 ], [ -50.19616, -21.45375 ], [ -50.19596, -21.45474 ], [ -50.19594, -21.45563 ] ] ], [ [ [ -50.19979, -21.45847 ], [ -50.20016, -21.45425 ], [ -50.19734, -21.45386 ], [ -50.19714, -21.45831 ], [ -50.19979, -21.45847 ] ] ] ] } },
{ "type": "Feature", "properties": { "NOME_FAZ": "FAZENDA SAO JOAO", "ZONA": 999, "TALHAO": 54, "AREA_TOTAL": 9.3719100030245261, "FAZENDA": "306829" }, "geometry": { "type": "Polygon", "coordinates": [ [ [ -50.19713, -21.45835 ], [ -50.19707, -21.45991 ], [ -50.19713, -21.46003 ], [ -50.1979, -21.46127 ], [ -50.19934, -21.46292 ], [ -50.19979, -21.4585 ], [ -50.19713, -21.45835 ] ] ] } },
{ "type": "Feature", "properties": { "NOME_FAZ": "FAZENDA SAO JOAO", "ZONA": 999, "TALHAO": 51, "AREA_TOTAL": 24.825948533873088, "FAZENDA": "306829" }, "geometry": { "type": "Polygon", "coordinates": [ [ [ -50.18383, -21.44899 ], [ -50.18922, -21.45368 ], [ -50.1898, -21.4542 ], [ -50.1901, -21.4504 ], [ -50.19005, -21.4501 ], [ -50.18533, -21.44657 ], [ -50.18383, -21.44899 ] ] ] } },
{ "type": "Feature", "properties": { "NOME_FAZ": "FAZENDA SAO JOAO", "ZONA": 999, "TALHAO": 50, "AREA_TOTAL": 26.339564210726994, "FAZENDA": "306829" }, "geometry": { "type": "Polygon", "coordinates": [ [ [ -50.18394, -21.44913 ], [ -50.18378, -21.44913 ], [ -50.18367, -21.44926 ], [ -50.18266, -21.45098 ], [ -50.18264, -21.45122 ], [ -50.18823, -21.45664 ], [ -50.18942, -21.45753 ], [ -50.18978, -21.4544 ], [ -50.18974, -21.45423 ], [ -50.18394, -21.44913 ] ] ] } },
{ "type": "Feature", "properties": { "NOME_FAZ": "FAZENDA SAO JOAO", "ZONA": 999, "TALHAO": 39, "AREA_TOTAL": 21.195252510794056, "FAZENDA": "306829" }, "geometry": { "type": "MultiPolygon", "coordinates": [ [ [ [ -50.20132, -21.47245 ], [ -50.2001, -21.47291 ], [ -50.19942, -21.47312 ], [ -50.20072, -21.47389 ], [ -50.20125, -21.47412 ], [ -50.20141, -21.4725 ], [ -50.20132, -21.47245 ] ] ], [ [ [ -50.20143, -21.47221 ], [ -50.2015, -21.47133 ], [ -50.20143, -21.47117 ], [ -50.19634, -21.46739 ], [ -50.19622, -21.46738 ], [ -50.1959, -21.47075 ], [ -50.19598, -21.47106 ], [ -50.19919, -21.47299 ], [ -50.20143, -21.47221 ] ] ] ] } },
{ "type": "Feature", "properties": { "NOME_FAZ": "FAZENDA SAO JOAO", "ZONA": 999, "TALHAO": 38, "AREA_TOTAL": 4.4975125924598061, "FAZENDA": "306829" }, "geometry": { "type": "Polygon", "coordinates": [ [ [ -50.19668, -21.47392 ], [ -50.19901, -21.47311 ], [ -50.19911, -21.47301 ], [ -50.19601, -21.47121 ], [ -50.19655, -21.47387 ], [ -50.19668, -21.47392 ] ] ] } },
{ "type": "Feature", "properties": { "NOME_FAZ": "FAZENDA SAO JOAO", "ZONA": 999, "TALHAO": 34, "AREA_TOTAL": 36.637680031554709, "FAZENDA": "306829" }, "geometry": { "type": "Polygon", "coordinates": [ [ [ -50.17427, -21.4135 ], [ -50.1742, -21.41382 ], [ -50.17443, -21.41528 ], [ -50.17461, -21.41761 ], [ -50.18079, -21.41507 ], [ -50.17954, -21.41013 ], [ -50.17945, -21.41034 ], [ -50.17888, -21.41081 ], [ -50.17847, -21.41096 ], [ -50.17801, -21.41102 ], [ -50.17763, -21.411 ], [ -50.1774, -21.41088 ], [ -50.17693, -21.41022 ], [ -50.1766, -21.41026 ], [ -50.17589, -21.4108 ], [ -50.1756, -21.41112 ], [ -50.17474, -21.41286 ], [ -50.17427, -21.4135 ] ] ] } },
{ "type": "Feature", "properties": { "NOME_FAZ": "FAZENDA SAO JOAO", "ZONA": 999, "TALHAO": 37, "AREA_TOTAL": 17.806096355052642, "FAZENDA": "306829" }, "geometry": { "type": "Polygon", "coordinates": [ [ [ -50.19921, -21.47322 ], [ -50.19664, -21.47416 ], [ -50.19681, -21.47505 ], [ -50.19702, -21.47566 ], [ -50.19751, -21.47625 ], [ -50.20086, -21.47853 ], [ -50.20103, -21.47742 ], [ -50.20128, -21.47423 ], [ -50.19948, -21.47323 ], [ -50.19921, -21.47322 ] ] ] } },
{ "type": "Feature", "properties": { "NOME_FAZ": "FAZENDA SAO JOAO", "ZONA": 999, "TALHAO": 36, "AREA_TOTAL": 19.011449975609047, "FAZENDA": "306829" }, "geometry": { "type": "Polygon", "coordinates": [ [ [ -50.17462, -21.41765 ], [ -50.17532, -21.42417 ], [ -50.17611, -21.42523 ], [ -50.17637, -21.42528 ], [ -50.1771, -21.42496 ], [ -50.17939, -21.42361 ], [ -50.17923, -21.42305 ], [ -50.17852, -21.4232 ], [ -50.17806, -21.42311 ], [ -50.1775, -21.42269 ], [ -50.1771, -21.4221 ], [ -50.1768, -21.4212 ], [ -50.1765, -21.41988 ], [ -50.1763, -21.41697 ], [ -50.17462, -21.41765 ] ] ] } },
{ "type": "Feature", "properties": { "NOME_FAZ": "FAZENDA SAO JOAO", "ZONA": 999, "TALHAO": 42, "AREA_TOTAL": 16.561810498378815, "FAZENDA": "306829" }, "geometry": { "type": "Polygon", "coordinates": [ [ [ -50.19251, -21.46476 ], [ -50.19222, -21.46832 ], [ -50.19579, -21.47092 ], [ -50.19605, -21.46853 ], [ -50.19611, -21.46725 ], [ -50.19258, -21.46464 ], [ -50.19251, -21.46476 ] ] ] } },
{ "type": "Feature", "properties": { "NOME_FAZ": "FAZENDA SAO JOAO", "ZONA": 999, "TALHAO": 41, "AREA_TOTAL": 16.457080297048787, "FAZENDA": "306829" }, "geometry": { "type": "Polygon", "coordinates": [ [ [ -50.19215, -21.46839 ], [ -50.18909, -21.46607 ], [ -50.18882, -21.46596 ], [ -50.18849, -21.46996 ], [ -50.19176, -21.47224 ], [ -50.19183, -21.47217 ], [ -50.19215, -21.46839 ] ] ] } },
{ "type": "Feature", "properties": { "NOME_FAZ": "FAZENDA SAO JOAO", "ZONA": 999, "TALHAO": 44, "AREA_TOTAL": 23.002954514734601, "FAZENDA": "306829" }, "geometry": { "type": "Polygon", "coordinates": [ [ [ -50.20161, -21.47108 ], [ -50.2019, -21.46789 ], [ -50.20185, -21.4677 ], [ -50.19765, -21.46444 ], [ -50.19698, -21.46383 ], [ -50.19665, -21.4638 ], [ -50.19637, -21.46684 ], [ -50.19639, -21.46731 ], [ -50.20154, -21.47113 ], [ -50.20161, -21.47108 ] ] ] } },
{ "type": "Feature", "properties": { "NOME_FAZ": "FAZENDA SAO JOAO", "ZONA": 999, "TALHAO": 43, "AREA_TOTAL": 15.362037887555712, "FAZENDA": "306829" }, "geometry": { "type": "Polygon", "coordinates": [ [ [ -50.18918, -21.46212 ], [ -50.18911, -21.4622 ], [ -50.18906, -21.46272 ], [ -50.18883, -21.46582 ], [ -50.19212, -21.46825 ], [ -50.19248, -21.46456 ], [ -50.18918, -21.46212 ] ] ] } },
{ "type": "Feature", "properties": { "NOME_FAZ": "FAZENDA SAO JOAO", "ZONA": 999, "TALHAO": 28, "AREA_TOTAL": 47.66561758205598, "FAZENDA": "306829" }, "geometry": { "type": "MultiPolygon", "coordinates": [ [ [ [ -50.18153, -21.40143 ], [ -50.1779, -21.40747 ], [ -50.17892, -21.40849 ], [ -50.1791, -21.40849 ], [ -50.18023, -21.40791 ], [ -50.18402, -21.40564 ], [ -50.18153, -21.40143 ] ] ], [ [ [ -50.18836, -21.40311 ], [ -50.18844, -21.403 ], [ -50.18839, -21.40288 ], [ -50.18796, -21.40233 ], [ -50.18662, -21.40149 ], [ -50.18291, -21.40374 ], [ -50.18405, -21.40563 ], [ -50.18836, -21.40311 ] ] ], [ [ [ -50.18289, -21.40371 ], [ -50.18658, -21.40146 ], [ -50.18588, -21.40104 ], [ -50.18492, -21.4003 ], [ -50.18467, -21.40031 ], [ -50.18412, -21.40061 ], [ -50.18328, -21.40079 ], [ -50.18316, -21.4007 ], [ -50.18289, -21.39987 ], [ -50.18273, -21.39975 ], [ -50.18104, -21.40035 ], [ -50.18105, -21.40048 ], [ -50.18289, -21.40371 ] ] ] ] } },
{ "type": "Feature", "properties": { "NOME_FAZ": "FAZENDA SAO JOAO", "ZONA": 999, "TALHAO": 27, "AREA_TOTAL": 27.890926823686229, "FAZENDA": "306829" }, "geometry": { "type": "Polygon", "coordinates": [ [ [ -50.19918, -21.43255 ], [ -50.19881, -21.43622 ], [ -50.20447, -21.43517 ], [ -50.20503, -21.43014 ], [ -50.19918, -21.43255 ] ] ] } },
{ "type": "Feature", "properties": { "NOME_FAZ": "FAZENDA SAO JOAO", "ZONA": 999, "TALHAO": 29, "AREA_TOTAL": 52.863754613066561, "FAZENDA": "306829" }, "geometry": { "type": "MultiPolygon", "coordinates": [ [ [ [ -50.20507, -21.43007 ], [ -50.20707, -21.4281 ], [ -50.20285, -21.42426 ], [ -50.19963, -21.42678 ], [ -50.20075, -21.42813 ], [ -50.20161, -21.42944 ], [ -50.20174, -21.42992 ], [ -50.20176, -21.43038 ], [ -50.20153, -21.43149 ], [ -50.20507, -21.43007 ] ] ], [ [ [ -50.19644, -21.42279 ], [ -50.19961, -21.42676 ], [ -50.20282, -21.42424 ], [ -50.19903, -21.42074 ], [ -50.19644, -21.42279 ] ] ] ] } },
{ "type": "Feature", "properties": { "NOME_FAZ": "FAZENDA SAO JOAO", "ZONA": 999, "TALHAO": 24, "AREA_TOTAL": 12.126597124315799, "FAZENDA": "306829" }, "geometry": { "type": "Polygon", "coordinates": [ [ [ -50.19729, -21.42811 ], [ -50.19418, -21.4313 ], [ -50.19476, -21.43303 ], [ -50.19777, -21.43149 ], [ -50.19832, -21.43139 ], [ -50.19837, -21.43118 ], [ -50.19783, -21.42964 ], [ -50.19766, -21.42785 ], [ -50.19729, -21.42811 ] ] ] } },
{ "type": "Feature", "properties": { "NOME_FAZ": "FAZENDA SAO JOAO", "ZONA": 999, "TALHAO": 23, "AREA_TOTAL": 41.603319732152464, "FAZENDA": "306829" }, "geometry": { "type": "MultiPolygon", "coordinates": [ [ [ [ -50.19415, -21.43133 ], [ -50.18981, -21.43499 ], [ -50.18996, -21.4352 ], [ -50.19026, -21.43541 ], [ -50.19084, -21.43559 ], [ -50.19121, -21.43557 ], [ -50.19187, -21.43536 ], [ -50.19216, -21.43518 ], [ -50.1936, -21.43356 ], [ -50.19389, -21.43335 ], [ -50.19473, -21.43304 ], [ -50.19415, -21.43133 ] ] ], [ [ [ -50.1886, -21.42953 ], [ -50.18798, -21.43048 ], [ -50.18797, -21.43082 ], [ -50.1882, -21.43124 ], [ -50.18896, -21.43209 ], [ -50.18958, -21.43399 ], [ -50.18979, -21.43496 ], [ -50.19414, -21.43129 ], [ -50.19299, -21.42804 ], [ -50.19156, -21.42667 ], [ -50.18844, -21.42925 ], [ -50.1886, -21.42953 ] ] ] ] } },
{ "type": "Feature", "properties": { "NOME_FAZ": "FAZENDA SAO JOAO", "ZONA": 999, "TALHAO": 26, "AREA_TOTAL": 25.466985035682935, "FAZENDA": "306829" }, "geometry": { "type": "Polygon", "coordinates": [ [ [ -50.1988, -21.43627 ], [ -50.1985, -21.44022 ], [ -50.20387, -21.43932 ], [ -50.20405, -21.4392 ], [ -50.20446, -21.43521 ], [ -50.1988, -21.43627 ] ] ] } },
{ "type": "Feature", "properties": { "NOME_FAZ": "FAZENDA SAO JOAO", "ZONA": 999, "TALHAO": 25, "AREA_TOTAL": 45.13847293191192, "FAZENDA": "306829" }, "geometry": { "type": "MultiPolygon", "coordinates": [ [ [ [ -50.19333, -21.43948 ], [ -50.1936, -21.44006 ], [ -50.19377, -21.44015 ], [ -50.19664, -21.44032 ], [ -50.19777, -21.44032 ], [ -50.19845, -21.44023 ], [ -50.19876, -21.43628 ], [ -50.19326, -21.43732 ], [ -50.19306, -21.43841 ], [ -50.19333, -21.43948 ] ] ], [ [ [ -50.19467, -21.43311 ], [ -50.19327, -21.43727 ], [ -50.19876, -21.43623 ], [ -50.1991, -21.43283 ], [ -50.19836, -21.43262 ], [ -50.19773, -21.43155 ], [ -50.19467, -21.43311 ] ] ] ] } },
{ "type": "Feature", "properties": { "NOME_FAZ": "FAZENDA SAO JOAO", "ZONA": 999, "TALHAO": 31, "AREA_TOTAL": 42.329484394858035, "FAZENDA": "306829" }, "geometry": { "type": "MultiPolygon", "coordinates": [ [ [ [ -50.20904, -21.42611 ], [ -50.21175, -21.42329 ], [ -50.20908, -21.4216 ], [ -50.20866, -21.42127 ], [ -50.20776, -21.42032 ], [ -50.2051, -21.42247 ], [ -50.20904, -21.42611 ] ] ], [ [ [ -50.20507, -21.42245 ], [ -50.20774, -21.42029 ], [ -50.20439, -21.41666 ], [ -50.20417, -21.41658 ], [ -50.20126, -21.41893 ], [ -50.20507, -21.42245 ] ] ] ] } },
{ "type": "Feature", "properties": { "NOME_FAZ": "FAZENDA SAO JOAO", "ZONA": 999, "TALHAO": 33, "AREA_TOTAL": 54.614213631579076, "FAZENDA": "306829" }, "geometry": { "type": "Polygon", "coordinates": [ [ [ -50.18083, -21.4151 ], [ -50.1815, -21.41761 ], [ -50.18174, -21.41769 ], [ -50.18336, -21.41886 ], [ -50.18433, -21.41988 ], [ -50.18588, -21.41975 ], [ -50.18752, -21.41937 ], [ -50.18889, -21.41853 ], [ -50.19063, -21.41763 ], [ -50.19078, -21.41747 ], [ -50.19077, -21.41734 ], [ -50.19006, -21.41603 ], [ -50.18784, -21.41216 ], [ -50.18083, -21.4151 ] ] ] } },
{ "type": "Feature", "properties": { "NOME_FAZ": "FAZENDA SAO JOAO", "ZONA": 999, "TALHAO": 32, "AREA_TOTAL": 51.985547435162175, "FAZENDA": "306829" }, "geometry": { "type": "Polygon", "coordinates": [ [ [ -50.17954, -21.40996 ], [ -50.18082, -21.41506 ], [ -50.18782, -21.41212 ], [ -50.18567, -21.40834 ], [ -50.18466, -21.40678 ], [ -50.18434, -21.40614 ], [ -50.18421, -21.40603 ], [ -50.18392, -21.40606 ], [ -50.18325, -21.40639 ], [ -50.1793, -21.40876 ], [ -50.17915, -21.40892 ], [ -50.17913, -21.40907 ], [ -50.17954, -21.40996 ] ] ] } },
{ "type": "Feature", "properties": { "NOME_FAZ": "FAZENDA SAO JOAO", "ZONA": 999, "TALHAO": 17, "AREA_TOTAL": 33.410124978170714, "FAZENDA": "306829" }, "geometry": { "type": "Polygon", "coordinates": [ [ [ -50.19526, -21.41737 ], [ -50.1985, -21.42021 ], [ -50.19866, -21.4194 ], [ -50.19898, -21.4184 ], [ -50.19903, -21.41776 ], [ -50.19925, -21.41746 ], [ -50.1994, -21.41745 ], [ -50.19956, -21.41763 ], [ -50.20039, -21.41906 ], [ -50.20055, -21.41947 ], [ -50.20407, -21.41661 ], [ -50.20175, -21.41486 ], [ -50.20056, -21.41318 ], [ -50.1972, -21.41498 ], [ -50.19702, -21.41522 ], [ -50.19704, -21.41546 ], [ -50.19735, -21.41621 ], [ -50.19526, -21.41737 ] ] ] } },
{ "type": "Feature", "properties": { "NOME_FAZ": "FAZENDA SAO JOAO", "ZONA": 999, "TALHAO": 19, "AREA_TOTAL": 41.753439907035791, "FAZENDA": "306829" }, "geometry": { "type": "MultiPolygon", "coordinates": [ [ [ [ -50.20824, -21.43203 ], [ -50.21317, -21.43507 ], [ -50.21335, -21.43507 ], [ -50.21448, -21.43115 ], [ -50.21131, -21.42888 ], [ -50.20824, -21.43203 ] ] ], [ [ [ -50.20516, -21.43013 ], [ -50.20821, -21.43201 ], [ -50.21128, -21.42886 ], [ -50.20845, -21.42681 ], [ -50.20516, -21.43013 ] ] ] ] } },
{ "type": "Feature", "properties": { "NOME_FAZ": "FAZENDA SAO JOAO", "ZONA": 999, "TALHAO": 18, "AREA_TOTAL": 37.401851985764502, "FAZENDA": "306829" }, "geometry": { "type": "MultiPolygon", "coordinates": [ [ [ [ -50.18822, -21.41978 ], [ -50.19316, -21.4215 ], [ -50.19627, -21.42288 ], [ -50.19653, -21.42268 ], [ -50.19134, -21.41809 ], [ -50.18822, -21.41978 ] ] ], [ [ [ -50.19138, -21.41807 ], [ -50.19656, -21.42266 ], [ -50.199, -21.42072 ], [ -50.19523, -21.41739 ], [ -50.19462, -21.41639 ], [ -50.19138, -21.41807 ] ] ] ] } },
{ "type": "Feature", "properties": { "NOME_FAZ": "FAZENDA SAO JOAO", "ZONA": 999, "TALHAO": 13, "AREA_TOTAL": 42.108946957689959, "FAZENDA": "306829" }, "geometry": { "type": "MultiPolygon", "coordinates": [ [ [ [ -50.19761, -21.39809 ], [ -50.19585, -21.39907 ], [ -50.19572, -21.39922 ], [ -50.19873, -21.40351 ], [ -50.19989, -21.40537 ], [ -50.20067, -21.40697 ], [ -50.20077, -21.40697 ], [ -50.20094, -21.40682 ], [ -50.20091, -21.40536 ], [ -50.20201, -21.40117 ], [ -50.19761, -21.39809 ] ] ], [ [ [ -50.19768, -21.39801 ], [ -50.19767, -21.39808 ], [ -50.19996, -21.39971 ], [ -50.20203, -21.40108 ], [ -50.20335, -21.39661 ], [ -50.20278, -21.39661 ], [ -50.20228, -21.39688 ], [ -50.20157, -21.39744 ], [ -50.20096, -21.39766 ], [ -50.20082, -21.39758 ], [ -50.20017, -21.39668 ], [ -50.20003, -21.39664 ], [ -50.19768, -21.39801 ] ] ] ] } },
{ "type": "Feature", "properties": { "NOME_FAZ": "FAZENDA SAO JOAO", "ZONA": 999, "TALHAO": 12, "AREA_TOTAL": 46.411718941407258, "FAZENDA": "306829" }, "geometry": { "type": "MultiPolygon", "coordinates": [ [ [ [ -50.20797, -21.40829 ], [ -50.20829, -21.40819 ], [ -50.20844, -21.40758 ], [ -50.2087, -21.40729 ], [ -50.20934, -21.40715 ], [ -50.20956, -21.40723 ], [ -50.21025, -21.40705 ], [ -50.21041, -21.40694 ], [ -50.21036, -21.40542 ], [ -50.21047, -21.4039 ], [ -50.21023, -21.40328 ], [ -50.20986, -21.4027 ], [ -50.20666, -21.40442 ], [ -50.20797, -21.40829 ] ] ], [ [ [ -50.20743, -21.39852 ], [ -50.20505, -21.39971 ], [ -50.20665, -21.40438 ], [ -50.20984, -21.40267 ], [ -50.20889, -21.40119 ], [ -50.20743, -21.39852 ] ] ], [ [ [ -50.20637, -21.39574 ], [ -50.20494, -21.39403 ], [ -50.20355, -21.39473 ], [ -50.20368, -21.3953 ], [ -50.20366, -21.39594 ], [ -50.20398, -21.39653 ], [ -50.20504, -21.39968 ], [ -50.20742, -21.39849 ], [ -50.20637, -21.39574 ] ] ] ] } },
{ "type": "Feature", "properties": { "NOME_FAZ": "FAZENDA SAO JOAO", "ZONA": 999, "TALHAO": 15, "AREA_TOTAL": 21.51226292377299, "FAZENDA": "306829" }, "geometry": { "type": "Polygon", "coordinates": [ [ [ -50.19179, -21.39338 ], [ -50.1919, -21.39376 ], [ -50.19187, -21.39386 ], [ -50.19132, -21.39424 ], [ -50.19128, -21.39444 ], [ -50.19275, -21.39566 ], [ -50.19415, -21.39726 ], [ -50.19435, -21.39741 ], [ -50.19616, -21.3959 ], [ -50.19685, -21.39551 ], [ -50.19638, -21.39491 ], [ -50.19593, -21.39386 ], [ -50.19383, -21.39128 ], [ -50.19276, -21.39168 ], [ -50.19117, -21.39266 ], [ -50.19179, -21.39338 ] ] ] } },
{ "type": "Feature", "properties": { "NOME_FAZ": "FAZENDA SAO JOAO", "ZONA": 999, "TALHAO": 14, "AREA_TOTAL": 26.981778490936534, "FAZENDA": "306829" }, "geometry": { "type": "MultiPolygon", "coordinates": [ [ [ [ -50.19162, -21.40121 ], [ -50.19127, -21.40075 ], [ -50.1898, -21.39946 ], [ -50.18806, -21.39834 ], [ -50.18657, -21.39845 ], [ -50.1854, -21.39883 ], [ -50.18581, -21.3999 ], [ -50.18796, -21.40146 ], [ -50.1885, -21.40197 ], [ -50.18904, -21.40268 ], [ -50.19162, -21.40121 ] ] ], [ [ [ -50.19167, -21.40114 ], [ -50.19397, -21.39984 ], [ -50.19394, -21.39967 ], [ -50.19307, -21.39844 ], [ -50.19128, -21.39804 ], [ -50.18819, -21.39832 ], [ -50.18992, -21.39952 ], [ -50.19115, -21.40059 ], [ -50.19167, -21.40114 ] ] ] ] } },
{ "type": "Feature", "properties": { "NOME_FAZ": "FAZENDA SAO JOAO", "ZONA": 999, "TALHAO": 20, "AREA_TOTAL": 26.792311683143584, "FAZENDA": "306829" }, "geometry": { "type": "MultiPolygon", "coordinates": [ [ [ [ -50.21449, -21.43112 ], [ -50.21532, -21.42809 ], [ -50.21396, -21.42729 ], [ -50.21339, -21.42673 ], [ -50.21134, -21.42885 ], [ -50.21449, -21.43112 ] ] ], [ [ [ -50.21131, -21.42883 ], [ -50.21336, -21.42671 ], [ -50.2127, -21.42604 ], [ -50.21334, -21.42425 ], [ -50.21181, -21.42333 ], [ -50.20847, -21.42678 ], [ -50.21131, -21.42883 ] ] ] ] } },
{ "type": "Feature", "properties": { "NOME_FAZ": "FAZENDA SAO JOAO", "ZONA": 999, "TALHAO": 22, "AREA_TOTAL": 43.797254819877608, "FAZENDA": "306829" }, "geometry": { "type": "MultiPolygon", "coordinates": [ [ [ [ -50.18453, -21.42822 ], [ -50.18536, -21.42898 ], [ -50.18552, -21.42903 ], [ -50.18837, -21.42922 ], [ -50.19147, -21.42661 ], [ -50.18925, -21.42446 ], [ -50.18914, -21.42447 ], [ -50.18457, -21.42808 ], [ -50.18453, -21.42822 ] ] ], [ [ [ -50.18629, -21.42161 ], [ -50.18394, -21.42276 ], [ -50.1838, -21.42333 ], [ -50.18374, -21.42689 ], [ -50.1839, -21.42743 ], [ -50.18444, -21.42811 ], [ -50.18913, -21.42439 ], [ -50.18629, -21.42161 ] ] ] ] } },
{ "type": "Feature", "properties": { "NOME_FAZ": "FAZENDA SAO JOAO", "ZONA": 999, "TALHAO": 21, "AREA_TOTAL": 51.695008173765942, "FAZENDA": "306829" }, "geometry": { "type": "MultiPolygon", "coordinates": [ [ [ [ -50.19701, -21.42481 ], [ -50.19495, -21.42399 ], [ -50.19165, -21.42664 ], [ -50.19302, -21.42802 ], [ -50.19416, -21.43113 ], [ -50.19428, -21.43112 ], [ -50.19448, -21.43094 ], [ -50.19763, -21.42774 ], [ -50.19754, -21.42547 ], [ -50.19701, -21.42481 ] ] ], [ [ [ -50.1916, -21.42249 ], [ -50.18935, -21.42428 ], [ -50.18929, -21.42441 ], [ -50.19134, -21.42641 ], [ -50.1916, -21.42655 ], [ -50.19491, -21.42396 ], [ -50.1916, -21.42249 ] ] ], [ [ [ -50.1892, -21.42431 ], [ -50.1913, -21.42272 ], [ -50.1915, -21.42242 ], [ -50.18787, -21.42074 ], [ -50.18639, -21.42151 ], [ -50.18636, -21.42162 ], [ -50.1867, -21.42197 ], [ -50.1892, -21.42431 ] ] ] ] } },
{ "type": "Feature", "properties": { "NOME_FAZ": "FAZENDA SAO JOAO", "ZONA": 999, "TALHAO": 11, "AREA_TOTAL": 33.550165821479126, "FAZENDA": "306829" }, "geometry": { "type": "MultiPolygon", "coordinates": [ [ [ [ -50.2011, -21.40542 ], [ -50.20111, -21.40656 ], [ -50.20122, -21.40725 ], [ -50.2044, -21.40555 ], [ -50.20275, -21.40087 ], [ -50.20225, -21.40113 ], [ -50.2011, -21.40542 ] ] ], [ [ [ -50.20502, -21.39973 ], [ -50.20285, -21.40081 ], [ -50.2045, -21.4055 ], [ -50.20661, -21.4044 ], [ -50.20502, -21.39973 ] ] ], [ [ [ -50.20501, -21.39969 ], [ -50.20394, -21.39655 ], [ -50.20366, -21.396 ], [ -50.20349, -21.39699 ], [ -50.20226, -21.40108 ], [ -50.20501, -21.39969 ] ] ] ] } },
{ "type": "Feature", "properties": { "NOME_FAZ": "FAZENDA SAO JOAO", "ZONA": 999, "TALHAO": 10, "AREA_TOTAL": 30.964022007640615, "FAZENDA": "306829" }, "geometry": { "type": "MultiPolygon", "coordinates": [ [ [ [ -50.20123, -21.40729 ], [ -50.20153, -21.4102 ], [ -50.20185, -21.41169 ], [ -50.20582, -21.40954 ], [ -50.20441, -21.40559 ], [ -50.20123, -21.40729 ] ] ], [ [ [ -50.20586, -21.40951 ], [ -50.2077, -21.40852 ], [ -50.20794, -21.40831 ], [ -50.20662, -21.40444 ], [ -50.20452, -21.40553 ], [ -50.20586, -21.40951 ] ] ] ] } },
{ "type": "Feature", "properties": { "NOME_FAZ": "FAZENDA SAO JOAO", "ZONA": 999, "TALHAO": 9, "AREA_TOTAL": 25.787323723056005, "FAZENDA": "306829" }, "geometry": { "type": "MultiPolygon", "coordinates": [ [ [ [ -50.21604, -21.42528 ], [ -50.21613, -21.42525 ], [ -50.21672, -21.42318 ], [ -50.21542, -21.42457 ], [ -50.21604, -21.42528 ] ] ], [ [ [ -50.21365, -21.4229 ], [ -50.21497, -21.42398 ], [ -50.2154, -21.42454 ], [ -50.21674, -21.4231 ], [ -50.21692, -21.42247 ], [ -50.21178, -21.41533 ], [ -50.21172, -21.41534 ], [ -50.21135, -21.4157 ], [ -50.21129, -21.41603 ], [ -50.21172, -21.41747 ], [ -50.21173, -21.41923 ], [ -50.21185, -21.42009 ], [ -50.21224, -21.42109 ], [ -50.21365, -21.4229 ] ] ] ] } },
{ "type": "Feature", "properties": { "NOME_FAZ": "FAZENDA SAO JOAO", "ZONA": 999, "TALHAO": 30, "AREA_TOTAL": 34.035722994475904, "FAZENDA": "306829" }, "geometry": { "type": "MultiPolygon", "coordinates": [ [ [ [ -50.20288, -21.42424 ], [ -50.2071, -21.42807 ], [ -50.20902, -21.42614 ], [ -50.20507, -21.4225 ], [ -50.20288, -21.42424 ] ] ], [ [ [ -50.20504, -21.42247 ], [ -50.20124, -21.41895 ], [ -50.19906, -21.42072 ], [ -50.20285, -21.42421 ], [ -50.20504, -21.42247 ] ] ], [ [ [ -50.19938, -21.42007 ], [ -50.19872, -21.42042 ], [ -50.19903, -21.42069 ], [ -50.19955, -21.42028 ], [ -50.19938, -21.42007 ] ] ] ] } },
{ "type": "Feature", "properties": { "NOME_FAZ": "FAZENDA SAO JOAO", "ZONA": 999, "TALHAO": 16, "AREA_TOTAL": 29.66420156253098, "FAZENDA": "306829" }, "geometry": { "type": "MultiPolygon", "coordinates": [ [ [ [ -50.19616, -21.39424 ], [ -50.19641, -21.39489 ], [ -50.19688, -21.3955 ], [ -50.20206, -21.39348 ], [ -50.20206, -21.39342 ], [ -50.20158, -21.39301 ], [ -50.20024, -21.39228 ], [ -50.19947, -21.39164 ], [ -50.19887, -21.39099 ], [ -50.19868, -21.39107 ], [ -50.19854, -21.39129 ], [ -50.1979, -21.39133 ], [ -50.19773, -21.39127 ], [ -50.19758, -21.39113 ], [ -50.19719, -21.39035 ], [ -50.197, -21.39032 ], [ -50.19387, -21.39127 ], [ -50.19578, -21.3936 ], [ -50.19616, -21.39424 ] ] ], [ [ [ -50.20184, -21.39312 ], [ -50.20229, -21.39166 ], [ -50.2021, -21.3914 ], [ -50.20134, -21.39094 ], [ -50.20122, -21.39104 ], [ -50.20062, -21.39248 ], [ -50.20184, -21.39312 ] ] ], [ [ [ -50.19892, -21.39098 ], [ -50.19975, -21.39185 ], [ -50.20059, -21.39246 ], [ -50.2007, -21.39227 ], [ -50.19995, -21.39173 ], [ -50.19954, -21.39132 ], [ -50.19962, -21.39097 ], [ -50.20013, -21.39096 ], [ -50.20064, -21.3907 ], [ -50.20082, -21.3905 ], [ -50.20083, -21.3903 ], [ -50.20015, -21.38946 ], [ -50.19897, -21.38992 ], [ -50.19911, -21.39055 ], [ -50.19924, -21.39076 ], [ -50.19892, -21.39098 ] ] ] ] } },
{ "type": "Feature", "properties": { "NOME_FAZ": "FAZENDA SAO JOAO", "ZONA": 999, "TALHAO": 40, "AREA_TOTAL": 20.034236916045227, "FAZENDA": "306829" }, "geometry": { "type": "MultiPolygon", "coordinates": [ [ [ [ -50.19516, -21.47459 ], [ -50.19651, -21.47554 ], [ -50.1967, -21.4755 ], [ -50.19676, -21.47527 ], [ -50.1965, -21.47412 ], [ -50.19516, -21.47459 ] ] ], [ [ [ -50.19647, -21.47395 ], [ -50.19603, -21.47176 ], [ -50.19582, -21.47106 ], [ -50.19238, -21.4685 ], [ -50.19222, -21.46845 ], [ -50.19188, -21.47232 ], [ -50.19494, -21.47445 ], [ -50.19647, -21.47395 ] ] ] ] } },
{ "type": "Feature", "properties": { "NOME_FAZ": "FAZENDA SAO JOAO", "ZONA": 999, "TALHAO": 49, "AREA_TOTAL": 28.319248354535947, "FAZENDA": "306829" }, "geometry": { "type": "MultiPolygon", "coordinates": [ [ [ [ -50.19565, -21.45999 ], [ -50.19589, -21.46024 ], [ -50.19658, -21.46121 ], [ -50.19623, -21.46056 ], [ -50.19585, -21.45955 ], [ -50.19565, -21.45999 ] ] ], [ [ [ -50.19019, -21.45021 ], [ -50.18984, -21.45423 ], [ -50.19417, -21.45844 ], [ -50.19563, -21.45996 ], [ -50.19583, -21.4595 ], [ -50.19534, -21.45817 ], [ -50.19487, -21.45648 ], [ -50.19465, -21.45378 ], [ -50.19234, -21.45186 ], [ -50.19019, -21.45021 ] ] ] ] } },
{ "type": "Feature", "properties": { "NOME_FAZ": "FAZENDA SAO JOAO", "ZONA": 999, "TALHAO": 52, "AREA_TOTAL": 24.151351641786448, "FAZENDA": "306829" }, "geometry": { "type": "MultiPolygon", "coordinates": [ [ [ [ -50.19464, -21.45372 ], [ -50.19458, -21.45232 ], [ -50.19451, -21.45169 ], [ -50.1942, -21.45338 ], [ -50.19464, -21.45372 ] ] ], [ [ [ -50.19416, -21.45336 ], [ -50.1945, -21.45159 ], [ -50.19414, -21.44996 ], [ -50.19149, -21.44497 ], [ -50.19115, -21.44369 ], [ -50.1908, -21.44308 ], [ -50.19049, -21.44606 ], [ -50.19019, -21.45013 ], [ -50.19237, -21.45183 ], [ -50.19416, -21.45336 ] ] ] ] } },
{ "type": "Feature", "properties": { "NOME_FAZ": "FAZENDA SAO JOAO", "ZONA": 999, "TALHAO": 35, "AREA_TOTAL": 48.428028825070406, "FAZENDA": "306829" }, "geometry": { "type": "MultiPolygon", "coordinates": [ [ [ [ -50.17487, -21.4204 ], [ -50.17399, -21.42267 ], [ -50.17407, -21.423 ], [ -50.17527, -21.42413 ], [ -50.17487, -21.4204 ] ] ], [ [ [ -50.1763, -21.41696 ], [ -50.17653, -21.42006 ], [ -50.17692, -21.42161 ], [ -50.17717, -21.42224 ], [ -50.17761, -21.42279 ], [ -50.17812, -21.42314 ], [ -50.17856, -21.42319 ], [ -50.17923, -21.42304 ], [ -50.17881, -21.42176 ], [ -50.1775, -21.41648 ], [ -50.1763, -21.41696 ] ] ], [ [ [ -50.18032, -21.42307 ], [ -50.18279, -21.4219 ], [ -50.18328, -21.42133 ], [ -50.18377, -21.42061 ], [ -50.18386, -21.42036 ], [ -50.18379, -21.42014 ], [ -50.18351, -21.41979 ], [ -50.18143, -21.41775 ], [ -50.18146, -21.41763 ], [ -50.1808, -21.41511 ], [ -50.17754, -21.41646 ], [ -50.17942, -21.42359 ], [ -50.18032, -21.42307 ] ] ] ] } }
]
}
