{
"type": "FeatureCollection",
"name": "divisas_301474",
"crs": { "type": "name", "properties": { "name": "urn:ogc:def:crs:OGC:1.3:CRS84" } },
"features": [
{ "type": "Feature", "properties": { "NOME_FAZ": "ESTANCIA AIMORES I E II", "ZONA": 1, "TALHAO": 1, "AREA_TOTAL": 25.820553580269493, "FAZENDA": "301474" }, "geometry": { "type": "Polygon", "coordinates": [ [ [ -50.34728, -21.80054 ], [ -50.34605, -21.79837 ], [ -50.34167, -21.80367 ], [ -50.34165, -21.80381 ], [ -50.34543, -21.80586 ], [ -50.3478, -21.80132 ], [ -50.34782, -21.80124 ], [ -50.34734, -21.8006 ], [ -50.34723, -21.80062 ], [ -50.34728, -21.80054 ] ] ] } },
{ "type": "Feature", "properties": { "NOME_FAZ": "ESTANCIA AIMORES I E II", "ZONA": 1, "TALHAO": 3, "AREA_TOTAL": 3.4024779470227542, "FAZENDA": "301474" }, "geometry": { "type": "Polygon", "coordinates": [ [ [ -50.35067, -21.79526 ], [ -50.35081, -21.79482 ], [ -50.35086, -21.79389 ], [ -50.35056, -21.79331 ], [ -50.35041, -21.79325 ], [ -50.3492, -21.79461 ], [ -50.34852, -21.79551 ], [ -50.34855, -21.7956 ], [ -50.34962, -21.79546 ], [ -50.34991, -21.79533 ], [ -50.35045, -21.79539 ], [ -50.35067, -21.79526 ] ] ] } },
{ "type": "Feature", "properties": { "NOME_FAZ": "ESTANCIA AIMORES I E II", "ZONA": 1, "TALHAO": 2, "AREA_TOTAL": 13.683103759104526, "FAZENDA": "301474" }, "geometry": { "type": "Polygon", "coordinates": [ [ [ -50.34985, -21.79557 ], [ -50.3483, -21.79576 ], [ -50.34711, -21.79714 ], [ -50.3469, -21.79754 ], [ -50.34661, -21.79775 ], [ -50.34616, -21.79831 ], [ -50.34747, -21.80065 ], [ -50.34783, -21.80106 ], [ -50.34803, -21.80097 ], [ -50.35061, -21.79581 ], [ -50.35052, -21.79572 ], [ -50.34985, -21.79557 ] ] ] } }
]
}
