{
"type": "FeatureCollection",
"name": "divisas_307270",
"crs": { "type": "name", "properties": { "name": "urn:ogc:def:crs:OGC:1.3:CRS84" } },
"features": [
{ "type": "Feature", "properties": { "NOME_FAZ": "SITIO SAO PEDRO", "ZONA": 999, "TALHAO": 1, "AREA_TOTAL": 17.567433018985877, "FAZENDA": "307270" }, "geometry": { "type": "Polygon", "coordinates": [ [ [ -50.26562, -21.48697 ], [ -50.26468, -21.48777 ], [ -50.2619, -21.49034 ], [ -50.26121, -21.49092 ], [ -50.26101, -21.4911 ], [ -50.26087, -21.49125 ], [ -50.26087, -21.49132 ], [ -50.26104, -21.49151 ], [ -50.26132, -21.49188 ], [ -50.26141, -21.49207 ], [ -50.26149, -21.49219 ], [ -50.26191, -21.49271 ], [ -50.26208, -21.49288 ], [ -50.26212, -21.49288 ], [ -50.26222, -21.4928 ], [ -50.26775, -21.4879 ], [ -50.2682, -21.48749 ], [ -50.26567, -21.48696 ], [ -50.26562, -21.48697 ] ] ] } }
]
}
